MANIFEST.in
README.md
setup.py
ceotr_styleguide.egg-info/PKG-INFO
ceotr_styleguide.egg-info/SOURCES.txt
ceotr_styleguide.egg-info/dependency_links.txt
ceotr_styleguide.egg-info/top_level.txt
ceotr_styleguide.egg-info/zip-safe
styleguide/__init__.py
styleguide/static/styleguide/.DS_Store
styleguide/static/styleguide/index.html
styleguide/static/styleguide/assets/images/ceotr.png
styleguide/static/styleguide/assets/images/gears.svg
styleguide/static/styleguide/assets/images/magic.svg
styleguide/static/styleguide/assets/images/unify.svg
styleguide/static/styleguide/assets/scss/_styleguideElements.scss
styleguide/static/styleguide/assets/scss/_styleguideObjects.scss
styleguide/static/styleguide/assets/scss/_styleguideVariables.scss
styleguide/static/styleguide/assets/scss/ceotr.css
styleguide/static/styleguide/assets/scss/ceotr.scss
styleguide/static/styleguide/assets/scss/style.css
styleguide/static/styleguide/assets/scss/style.scss