Metadata-Version: 2.1
Name: ceotr-styleguide
Version: 1.0.1
Summary: CEOTR styleguide
Home-page: https://gitlab.oceantrack.org/ceotr/styleguide.git
Author: CEOTR
Author-email: support@ceotr.ca
License: UNKNOWN
Platform: UNKNOWN
